odoo/addons/l10n_it_pos_fiscalcode/README.rst
odoo/addons/l10n_it_pos_fiscalcode/__init__.py
odoo/addons/l10n_it_pos_fiscalcode/__manifest__.py
odoo/addons/l10n_it_pos_fiscalcode/i18n/it.po
odoo/addons/l10n_it_pos_fiscalcode/i18n/l10n_it_pos_fiscalcode.pot
odoo/addons/l10n_it_pos_fiscalcode/models/__init__.py
odoo/addons/l10n_it_pos_fiscalcode/models/pos_session.py
odoo/addons/l10n_it_pos_fiscalcode/readme/CONTRIBUTORS.md
odoo/addons/l10n_it_pos_fiscalcode/readme/DESCRIPTION.md
odoo/addons/l10n_it_pos_fiscalcode/static/description/icon.png
odoo/addons/l10n_it_pos_fiscalcode/static/description/index.html
odoo/addons/l10n_it_pos_fiscalcode/static/src/xml/pos.xml
odoo_addon_l10n_it_pos_fiscalcode-16.0.1.0.0.7.dist-info/METADATA
odoo_addon_l10n_it_pos_fiscalcode-16.0.1.0.0.7.dist-info/WHEEL
odoo_addon_l10n_it_pos_fiscalcode-16.0.1.0.0.7.dist-info/top_level.txt
odoo_addon_l10n_it_pos_fiscalcode-16.0.1.0.0.7.dist-info/RECORD
